rtorrent/__init__.py
rtorrent/common.py
rtorrent/compat.py
rtorrent/err.py
rtorrent/file.py
rtorrent/group.py
rtorrent/peer.py
rtorrent/torrent.py
rtorrent/tracker.py
rtorrent/lib/__init__.py
rtorrent/lib/bencode.py
rtorrent/lib/torrentparser.py
rtorrent/lib/xmlrpc/__init__.py
rtorrent/lib/xmlrpc/basic_auth.py
rtorrent/lib/xmlrpc/http.py
rtorrent/lib/xmlrpc/scgi.py
rtorrent/rpc/__init__.py
rtorrent_python_dl-0.2.10.dist-info/METADATA
rtorrent_python_dl-0.2.10.dist-info/WHEEL
rtorrent_python_dl-0.2.10.dist-info/top_level.txt
rtorrent_python_dl-0.2.10.dist-info/RECORD
