Metadata-Version: 2.1
Name: rtorrent-python-dl
Version: 0.2.10
Summary: A simple rTorrent interface written in Python
Home-page: https://github.com/dloose/rtorrent-python
Author: Dave Loose
Author-email: daveloosenpm@gmail.com
Maintainer: Dave Loose
Maintainer-email: daveloosenpm@gmail.com
License: MIT
Keywords: rtorrent p2p
Platform: UNKNOWN
Classifier: Development Status :: 4 - Beta
Classifier: Intended Audience :: Developers
Classifier: License :: OSI Approved :: MIT License
Classifier: Natural Language :: English
Classifier: Operating System :: OS Independent
Classifier: Programming Language :: Python
Classifier: Topic :: Communications :: File Sharing
Classifier: Topic :: Software Development :: Libraries :: Python Modules
